pushjet/__init__.py
pushjet/errors.py
pushjet/pushjet.py
pushjet/utilities.py
pushjet-1.0.0.dist-info/DESCRIPTION.rst
pushjet-1.0.0.dist-info/METADATA
pushjet-1.0.0.dist-info/RECORD
pushjet-1.0.0.dist-info/WHEEL
pushjet-1.0.0.dist-info/metadata.json
pushjet-1.0.0.dist-info/top_level.txt
