Metadata-Version: 2.0
Name: pushjet
Version: 1.0.0
Summary: A Python API for Pushjet. Send notifications to your phone from Python scripts!
Home-page: https://github.com/obskyr/pushjet-py
Author: Samuel Messner
Author-email: powpowd@gmail.com
License: MIT
Download-URL: https://github.com/obskyr/pushjet-py/tarball/v1.0.0
Keywords: pushjet notifications android phone api rest
Platform: UNKNOWN
Classifier: Development Status :: 5 - Production/Stable
Classifier: Intended Audience :: Developers
Classifier: Programming Language :: Python
Classifier: Natural Language :: English
Classifier: License :: OSI Approved :: MIT License
Classifier: Programming Language :: Python :: 2.7
Classifier: Programming Language :: Python :: 3
Classifier: Programming Language :: Python :: 3.2
Classifier: Programming Language :: Python :: 3.3
Classifier: Programming Language :: Python :: 3.4
Classifier: Programming Language :: Python :: 3.5
Classifier: Topic :: Software Development :: Libraries :: Python Modules
Classifier: Topic :: Utilities
Requires-Dist: decorator (>=4.0.6,<5.0.0)
Requires-Dist: requests (>=2.11.1,<3.0.0)
